kpc/__about__.py
kpc/__init__.py
kpc-0.3.3.data/data/COPYRIGHT
kpc-0.3.3.data/data/LICENSE
kpc-0.3.3.dist-info/LICENSE
kpc-0.3.3.dist-info/METADATA
kpc-0.3.3.dist-info/WHEEL
kpc-0.3.3.dist-info/entry_points.txt
kpc-0.3.3.dist-info/top_level.txt
kpc-0.3.3.dist-info/RECORD
