Metadata-Version: 2.1
Name: kpc
Version: 0.3.3
Summary: KP Service Console
Home-page: https://github.com/mcode-cc/kpc
Author: MCode GmbH
Author-email: kpc@mcode.cc
License: GNU GENERAL PUBLIC LICENSE Version 3, 29 June 2007
Project-URL: Bug Tracker, https://github.com/mcode-cc/kpc/issues
Keywords: kpc console
Platform: Any
Classifier: License :: OSI Approved :: GNU Affero General Public License v3
Classifier: Development Status :: 1 - Planning
Classifier: Environment :: No Input/Output (Daemon)
Classifier: Environment :: Console
Classifier: Intended Audience :: Developers
Classifier: Operating System :: OS Independent
Classifier: Programming Language :: Python :: 3.6
Classifier: Programming Language :: Python :: 3.7
Classifier: Programming Language :: Python :: Implementation :: CPython
Classifier: Programming Language :: Python :: Implementation :: PyPy
Classifier: Topic :: Internet
Classifier: Topic :: Communications
Classifier: Topic :: Database
Classifier: Topic :: Software Development :: Libraries
Classifier: Topic :: Software Development :: Libraries :: Application Frameworks
Classifier: Topic :: System :: Networking
Requires-Python: >=3.6
License-File: LICENSE
